ut_dfr/__init__.py
ut_dfr/__version__.py
ut_dfr/pddf.py
ut_dfr/pldf.py
ut_dfr/py.typed
ut_dfr-2.0.0.20251020.dist-info/licenses/LICENSE.txt
ut_dfr-2.0.0.20251020.dist-info/METADATA
ut_dfr-2.0.0.20251020.dist-info/WHEEL
ut_dfr-2.0.0.20251020.dist-info/top_level.txt
ut_dfr-2.0.0.20251020.dist-info/RECORD
