Metadata-Version: 2.4
Name: ut_dfr
Version: 2.0.0.20251020
Summary: Utilities for Dataframes (Pandas, Polars).
Author-email: Bernd Stroehle <bernd.stroehle@gmail.com>
Maintainer-email: Bernd Stroehle <bernd.stroehle@gmail.com>
License-Expression: GPL-3.0-only WITH Classpath-exception-2.0 OR BSD-3-Clause
Project-URL: Source Code, https://github.com/bs29/ut_dfr/tree/master
Project-URL: Homepage, https://kosakya.de/
Project-URL: Documentation, https://ut-dfr.readthedocs.io/en/latest
Project-URL: Apache-2.0 License, https://apache.org/licenses/LICENSE-2.0
Project-URL: GPLv3 License, https://www.gnu.org/licenses/gpl-3.0.en.html
Classifier: Development Status :: 5 - Production/Stable
Classifier: Intended Audience :: Developers
Classifier: Operating System :: OS Independent
Classifier: Programming Language :: Python :: 3.13
Classifier: Natural Language :: English
Classifier: Topic :: Software Development :: Libraries :: Python Modules
Requires-Python: >=3.10
License-File: LICENSE.txt
Requires-Dist: pandas>=2.3.2
Requires-Dist: polars>=1.33.1
Requires-Dist: ut_log>=2.0.0.20251013
Dynamic: license-file
